auditlog/__init__.py
auditlog/admin.py
auditlog/apps.py
auditlog/databaserouter.py
auditlog/models.py
auditlog/tests.py
auditlog/triggers.py
auditlog/views.py
auditlog/migrations/0001_initial.py
auditlog/migrations/0002_auto_20190913_0219.py
auditlog/migrations/0003_auditlog_objeto.py
auditlog/migrations/__init__.py
django_auditorialog-0.1.dist-info/LICENSE
django_auditorialog-0.1.dist-info/METADATA
django_auditorialog-0.1.dist-info/WHEEL
django_auditorialog-0.1.dist-info/top_level.txt
django_auditorialog-0.1.dist-info/RECORD
